README.md
setup.cfg
setup.py
sdc_engine_helpers/__init__.py
sdc_engine_helpers/date_utils.py
sdc_engine_helpers/decorators.py
sdc_engine_helpers/engine_query_helper.py
sdc_engine_helpers/manager.py
sdc_engine_helpers.egg-info/PKG-INFO
sdc_engine_helpers.egg-info/SOURCES.txt
sdc_engine_helpers.egg-info/dependency_links.txt
sdc_engine_helpers.egg-info/requires.txt
sdc_engine_helpers.egg-info/top_level.txt
sdc_engine_helpers/glue_jobs/maintenance/__init__.py
sdc_engine_helpers/glue_jobs/maintenance/maintenance_manager.py
sdc_engine_helpers/glue_jobs/maintenance/pipeline_state_manager.py
sdc_engine_helpers/models/__init__.py
sdc_engine_helpers/models/service.py
sdc_engine_helpers/models/subscription.py
sdc_engine_helpers/personalize/__init__.py
sdc_engine_helpers/personalize/manager.py
sdc_engine_helpers/personalize/event/__init__.py
sdc_engine_helpers/personalize/event/event_manager.py
sdc_engine_helpers/personalize/maintenance/__init__.py
sdc_engine_helpers/personalize/maintenance/campaign_state_manager.py
sdc_engine_helpers/personalize/maintenance/maintenance_manager.py
sdc_engine_helpers/personalize/maintenance/solution_state_manager.py
sdc_engine_helpers/personalize/recommendations/__init__.py
sdc_engine_helpers/personalize/recommendations/recommendations_manager.py
sdc_engine_helpers/sagemaker/__init__.py
sdc_engine_helpers/sagemaker/sagemaker_query_helpers.py
sdc_engine_helpers/sagemaker/utils.py
sdc_engine_helpers/sagemaker/maintenance/__init__.py
sdc_engine_helpers/sagemaker/maintenance/campaign_state_manager.py
sdc_engine_helpers/sagemaker/maintenance/dataset_state_manager.py
sdc_engine_helpers/sagemaker/maintenance/maintenance_manager.py
sdc_engine_helpers/sagemaker/maintenance/solution_state_manager.py
sdc_engine_helpers/sagemaker/recommendations/__init__.py
sdc_engine_helpers/sagemaker/recommendations/recommendations_manager.py