Metadata-Version: 1.1
Name: sdc-engine-helpers
Version: 1.11.0
Summary: AWS Recommendation Engine Helpers
Home-page: http://github.com/RingierIMU/sdc-recommend-engine-helpers
Author: Ringier South Africa
Author-email: tools@ringier.co.za
License: UNKNOWN
Download-URL: https://github.com/RingierIMU/sdc-recommend-engine-helpers/archive/v1.9.2.zip
Keywords: pip,helpers,aws,recommendation,personalize,sagemaker
Platform: UNKNOWN
